Workbook

Sheet HOY
B2: MEGA RIFA FUSA · HOY
B3: Lo único que hay que mirar cada día. Todo se calcula solo.
B5: PAGADOS | C5: =RESUMEN!$B$3 | D5: números con la plata verificada
B7: APARTADOS vivos | C7: =RESUMEN!$B$4 | D7: aún no cumplen 24 h
B9: LIBRES | C9: =RESUMEN!$B$5 | D9: lo que de verdad queda
B11: VENCIDOS por recuperar | C11: =RESUMEN!$B$6 | D11: se cayeron solos: vuélvelos a ofrecer hoy
B13: RITMO por día | C13: =RESUMEN!$B$13 | D13: para llegar al piso. Si pasa de 30, vas atrasado
B16: QUÉ HAGO HOY
B17: 1. Abro Nu y marco PAGADO lo que llegó: lleno una fila en COMPRADORES (número, nombre, teléfono, SI/NO, y SI/NO de The Ber Way).
B18: 2. Reviso las filas ROJAS de NUMEROS (apartados vencidos): les escribo y, si no responden, pongo LIBRE.
B19: 3. Publico la imagen del tablero con el contador real (lo de LIBRES de arriba).
A21: Para el detalle de la plata y las metas de cada domingo, mira la pestaña RESUMEN.

Sheet NUMEROS
A1: NUMERO | B1: ESTADO_MANUAL | C1: HORA_APARTADO | D1: VENDEDOR | E1: NOMBRE_PUBLICO | F1: SERIAL | G1: ESTADO | H1: VENCE_A | I1: NOTA
A2: 000 | B2: LIBRE | E2: =IF($G2<>"PAGADO","",IFERROR(IF(VLOOKUP($A2,COMPRADORES!$A:$D,4,FALSE)="NO","Reservado",LEFT(VLOOKUP($A2,COMPRADORES!$A:$D,2,FALSE),3)&"***"&IF(TRIM(MID(VLOOKUP($A2,COMPRADORES!$A:$D,2,FALSE)&" ",FIND(" ",VLOOKUP($A2,COMPRADORES!$A:$D,2,FALSE)&" ")+1,99))="",""," "&LEFT(TRIM(MID(VLOOKUP($A2,COMPRADORES!$A:$D,2,FALSE)&" ",FIND(" ",VLOOKUP($A2,COMPRADORES!$A:$D,2,FALSE)&" ")+1,99)),1)&".")),"")) | F2: =IF($B2="PAGADO",MID("ABCDEFGHIJ",INT(VALUE($A2)/100)+1,1)&"-"&$A2,"") | G2: =IF($B2="PAGADO","PAGADO",IF($B2="APARTADO",IF(NOT(ISNUMBER($C2)),"APARTADO",IF($C2<1,"APARTADO",IF(NOW()-$C2>1,"LIBRE","APARTADO"))),"LIBRE")) | H2: =IF($G2<>"APARTADO","",IF(NOT(ISNUMBER($C2)),"FALTA LA HORA",IF($C2<1,"FALTA LA FECHA",TEXT($C2+1,"dd/mm hh:mm"))))
A3: 001 | B3: LIBRE | E3: =IF($G3<>"PAGADO","",IFERROR(IF(VLOOKUP($A3,COMPRADORES!$A:$D,4,FALSE)="NO","Reservado",LEFT(VLOOKUP($A3,COMPRADORES!$A:$D,2,FALSE),3)&"***"&IF(TRIM(MID(VLOOKUP($A3,COMPRADORES!$A:$D,2,FALSE)&" ",FIND(" ",VLOOKUP($A3,COMPRADORES!$A:$D,2,FALSE)&" ")+1,99))="",""," "&LEFT(TRIM(MID(VLOOKUP($A3,COMPRADORES!$A:$D,2,FALSE)&" ",FIND(" ",VLOOKUP($A3,COMPRADORES!$A:$D,2,FALSE)&" ")+1,99)),1)&".")),"")) | F3: =IF($B3="PAGADO",MID("ABCDEFGHIJ",INT(VALUE($A3)/100)+1,1)&"-"&$A3,"") | G3: =IF($B3="PAGADO","PAGADO",IF($B3="APARTADO",IF(NOT(ISNUMBER($C3)),"APARTADO",IF($C3<1,"APARTADO",IF(NOW()-$C3>1,"LIBRE","APARTADO"))),"LIBRE")) | H3: =IF($G3<>"APARTADO","",IF(NOT(ISNUMBER($C3)),"FALTA LA HORA",IF($C3<1,"FALTA LA FECHA",TEXT($C3+1,"dd/mm hh:mm"))))
A4: 002 | B4: LIBRE | E4: =IF($G4<>"PAGADO","",IFERROR(IF(VLOOKUP($A4,COMPRADORES!$A:$D,4,FALSE)="NO","Reservado",LEFT(VLOOKUP($A4,COMPRADORES!$A:$D,2,FALSE),3)&"***"&IF(TRIM(MID(VLOOKUP($A4,COMPRADORES!$A:$D,2,FALSE)&" ",FIND(" ",VLOOKUP($A4,COMPRADORES!$A:$D,2,FALSE)&" ")+1,99))="",""," "&LEFT(TRIM(MID(VLOOKUP($A4,COMPRADORES!$A:$D,2,FALSE)&" ",FIND(" ",VLOOKUP($A4,COMPRADORES!$A:$D,2,FALSE)&" ")+1,99)),1)&".")),"")) | F4: =IF($B4="PAGADO",MID("ABCDEFGHIJ",INT(VALUE($A4)/100)+1,1)&"-"&$A4,"") | G4: =IF($B4="PAGADO","PAGADO",IF($B4="APARTADO",IF(NOT(ISNUMBER($C4)),"APARTADO",IF($C4<1,"APARTADO",IF(NOW()-$C4>1,"LIBRE","APARTADO"))),"LIBRE")) | H4: =IF($G4<>"APARTADO","",IF(NOT(ISNUMBER($C4)),"FALTA LA HORA",IF($C4<1,"FALTA LA FECHA",TEXT($C4+1,"dd/mm hh:mm"))))
A5: 003 | B5: LIBRE | E5: =IF($G5<>"PAGADO","",IFERROR(IF(VLOOKUP($A5,COMPRADORES!$A:$D,4,FALSE)="NO","Reservado",LEFT(VLOOKUP($A5,COMPRADORES!$A:$D,2,FALSE),3)&"***"&IF(TRIM(MID(VLOOKUP($A5,COMPRADORES!$A:$D,2,FALSE)&" ",FIND(" ",VLOOKUP($A5,COMPRADORES!$A:$D,2,FALSE)&" ")+1,99))="",""," "&LEFT(TRIM(MID(VLOOKUP($A5,COMPRADORES!$A:$D,2,FALSE)&" ",FIND(" ",VLOOKUP($A5,COMPRADORES!$A:$D,2,FALSE)&" ")+1,99)),1)&".")),"")) | F5: =IF($B5="PAGADO",MID("ABCDEFGHIJ",INT(VALUE($A5)/100)+1,1)&"-"&$A5,"") | G5: =IF($B5="PAGADO","PAGADO",IF($B5="APARTADO",IF(NOT(ISNUMBER($C5)),"APARTADO",IF($C5<1,"APARTADO",IF(NOW()-$C5>1,"LIBRE","APARTADO"))),"LIBRE")) | H5: =IF($G5<>"APARTADO","",IF(NOT(ISNUMBER($C5)),"FALTA LA HORA",IF($C5<1,"FALTA LA FECHA",TEXT($C5+1,"dd/mm hh:mm"))))
A6: 004 | B6: LIBRE | E6: =IF($G6<>"PAGADO","",IFERROR(IF(VLOOKUP($A6,COMPRADORES!$A:$D,4,FALSE)="NO","Reservado",LEFT(VLOOKUP($A6,COMPRADORES!$A:$D,2,FALSE),3)&"***"&IF(TRIM(MID(VLOOKUP($A6,COMPRADORES!$A:$D,2,FALSE)&" ",FIND(" ",VLOOKUP($A6,COMPRADORES!$A:$D,2,FALSE)&" ")+1,99))="",""," "&LEFT(TRIM(MID(VLOOKUP($A6,COMPRADORES!$A:$D,2,FALSE)&" ",FIND(" ",VLOOKUP($A6,COMPRADORES!$A:$D,2,FALSE)&" ")+1,99)),1)&".")),"")) | F6: =IF($B6="PAGADO",MID("ABCDEFGHIJ",INT(VALUE($A6)/100)+1,1)&"-"&$A6,"") | G6: =IF($B6="PAGADO","PAGADO",IF($B6="APARTADO",IF(NOT(ISNUMBER($C6)),"APARTADO",IF($C6<1,"APARTADO",IF(NOW()-$C6>1,"LIBRE","APARTADO"))),"LIBRE")) | H6: =IF($G6<>"APARTADO","",IF(NOT(ISNUMBER($C6)),"FALTA LA HORA",IF($C6<1,"FALTA LA FECHA",TEXT($C6+1,"dd/mm hh:mm"))))
A7: 005 | B7: LIBRE | E7: =IF($G7<>"PAGADO","",IFERROR(IF(VLOOKUP($A7,COMPRADORES!$A:$D,4,FALSE)="NO","Reservado",LEFT(VLOOKUP($A7,COMPRADORES!$A:$D,2,FALSE),3)&"***"&IF(TRIM(MID(VLOOKUP($A7,COMPRADORES!$A:$D,2,FALSE)&" ",FIND(" ",VLOOKUP($A7,COMPRADORES!$A:$D,2,FALSE)&" ")+1,99))="",""," "&LEFT(TRIM(MID(VLOOKUP($A7,COMPRADORES!$A:$D,2,FALSE)&" ",FIND(" ",VLOOKUP($A7,COMPRADORES!$A:$D,2,FALSE)&" ")+1,99)),1)&".")),"")) | F7: =IF($B7="PAGADO",MID("ABCDEFGHIJ",INT(VALUE($A7)/100)+1,1)&"-"&$A7,"") | G7: =IF($B7="PAGADO","PAGADO",IF($B7="APARTADO",IF(NOT(ISNUMBER($C7)),"APARTADO",IF($C7<1,"APARTADO",IF(NOW()-$C7>1,"LIBRE","APARTADO"))),"LIBRE")) | H7: =IF($G7<>"APARTADO","",IF(NOT(ISNUMBER($C7)),"FALTA LA HORA",IF($C7<1,"FALTA LA FECHA",TEXT($C7+1,"dd/mm hh:mm"))))
A8: 006 | B8: LIBRE | E8: =IF($G8<>"PAGADO","",IFERROR(IF(VLOOKUP($A8,COMPRADORES!$A:$D,4,FALSE)="NO","Reservado",LEFT(VLOOKUP($A8,COMPRADORES!$A:$D,2,FALSE),3)&"***"&IF(TRIM(MID(VLOOKUP($A8,COMPRADORES!$A:$D,2,FALSE)&" ",FIND(" ",VLOOKUP($A8,COMPRADORES!$A:$D,2,FALSE)&" ")+1,99))="",""," "&LEFT(TRIM(MID(VLOOKUP($A8,COMPRADORES!$A:$D,2,FALSE)&" ",FIND(" ",VLOOKUP($A8,COMPRADORES!$A:$D,2,FALSE)&" ")+1,99)),1)&".")),"")) | F8: =IF($B8="PAGADO",MID("ABCDEFGHIJ",INT(VALUE($A8)/100)+1,1)&"-"&$A8,"") | G8: =IF($B8="PAGADO","PAGADO",IF($B8="APARTADO",IF(NOT(ISNUMBER($C8)),"APARTADO",IF($C8<1,"APARTADO",IF(NOW()-$C8>1,"LIBRE","APARTADO"))),"LIBRE")) | H8: =IF($G8<>"APARTADO","",IF(NOT(ISNUMBER($C8)),"FALTA LA HORA",IF($C8<1,"FALTA LA FECHA",TEXT($C8+1,"dd/mm hh:mm"))))
A9: 007 | B9: LIBRE | E9: =IF($G9<>"PAGADO","",IFERROR(IF(VLOOKUP($A9,COMPRADORES!$A:$D,4,FALSE)="NO","Reservado",LEFT(VLOOKUP($A9,COMPRADORES!$A:$D,2,FALSE),3)&"***"&IF(TRIM(MID(VLOOKUP($A9,COMPRADORES!$A:$D,2,FALSE)&" ",FIND(" ",VLOOKUP($A9,COMPRADORES!$A:$D,2,FALSE)&" ")+1,99))="",""," "&LEFT(TRIM(MID(VLOOKUP($A9,COMPRADORES!$A:$D,2,FALSE)&" ",FIND(" ",VLOOKUP($A9,COMPRADORES!$A:$D,2,FALSE)&" ")+1,99)),1)&".")),"")) | F9: =IF($B9="PAGADO",MID("ABCDEFGHIJ",INT(VALUE($A9)/100)+1,1)&"-"&$A9,"") | G9: =IF($B9="PAGADO","PAGADO",IF($B9="APARTADO",IF(NOT(ISNUMBER($C9)),"APARTADO",IF($C9<1,"APARTADO",IF(NOW()-$C9>1,"LIBRE","APARTADO"))),"LIBRE")) | H9: =IF($G9<>"APARTADO","",IF(NOT(ISNUMBER($C9)),"FALTA LA HORA",IF($C9<1,"FALTA LA FECHA",TEXT($C9+1,"dd/mm hh:mm"))))
A10: 008 | B10: LIBRE | E10: =IF($G10<>"PAGADO","",IFERROR(IF(VLOOKUP($A10,COMPRADORES!$A:$D,4,FALSE)="NO","Reservado",LEFT(VLOOKUP($A10,COMPRADORES!$A:$D,2,FALSE),3)&"***"&IF(TRIM(MID(VLOOKUP($A10,COMPRADORES!$A:$D,2,FALSE)&" ",FIND(" ",VLOOKUP($A10,COMPRADORES!$A:$D,2,FALSE)&" ")+1,99))="",""," "&LEFT(TRIM(MID(VLOOKUP($A10,COMPRADORES!$A:$D,2,FALSE)&" ",FIND(" ",VLOOKUP($A10,COMPRADORES!$A:$D,2,FALSE)&" ")+1,99)),1)&".")),"")) | F10: =IF($B10="PAGADO",MID("ABCDEFGHIJ",INT(VALUE($A10)/100)+1,1)&"-"&$A10,"") | G10: =IF($B10="PAGADO","PAGADO",IF($B10="APARTADO",IF(NOT(ISNUMBER($C10)),"APARTADO",IF($C10<1,"APARTADO",IF(NOW()-$C10>1,"LIBRE","APARTADO"))),"LIBRE")) | H10: =IF($G10<>"APARTADO","",IF(NOT(ISNUMBER($C10)),"FALTA LA HORA",IF($C10<1,"FALTA LA FECHA",TEXT($C10+1,"dd/mm hh:mm"))))
A11: 009 | B11: LIBRE | E11: =IF($G11<>"PAGADO","",IFERROR(IF(VLOOKUP($A11,COMPRADORES!$A:$D,4,FALSE)="NO","Reservado",LEFT(VLOOKUP($A11,COMPRADORES!$A:$D,2,FALSE),3)&"***"&IF(TRIM(MID(VLOOKUP($A11,COMPRADORES!$A:$D,2,FALSE)&" ",FIND(" ",VLOOKUP($A11,COMPRADORES!$A:$D,2,FALSE)&" ")+1,99))="",""," "&LEFT(TRIM(MID(VLOOKUP($A11,COMPRADORES!$A:$D,2,FALSE)&" ",FIND(" ",VLOOKUP($A11,COMPRADORES!$A:$D,2,FALSE)&" ")+1,99)),1)&".")),"")) | F11: =IF($B11="PAGADO",MID("ABCDEFGHIJ",INT(VALUE($A11)/100)+1,1)&"-"&$A11,"") | G11: =IF($B11="PAGADO","PAGADO",IF($B11="APARTADO",IF(NOT(ISNUMBER($C11)),"APARTADO",IF($C11<1,"APARTADO",IF(NOW()-$C11>1,"LIBRE","APARTADO"))),"LIBRE")) | H11: =IF($G11<>"APARTADO","",IF(NOT(ISNUMBER($C11)),"FALTA LA HORA",IF($C11<1,"FALTA LA FECHA",TEXT($C11+1,"dd/mm hh:mm"))))
A12: 010 | B12: LIBRE | E12: =IF($G12<>"PAGADO","",IFERROR(IF(VLOOKUP($A12,COMPRADORES!$A:$D,4,FALSE)="NO","Reservado",LEFT(VLOOKUP($A12,COMPRADORES!$A:$D,2,FALSE),3)&"***"&IF(TRIM(MID(VLOOKUP($A12,COMPRADORES!$A:$D,2,FALSE)&" ",FIND(" ",VLOOKUP($A12,COMPRADORES!$A:$D,2,FALSE)&" ")+1,99))="",""," "&LEFT(TRIM(MID(VLOOKUP($A12,COMPRADORES!$A:$D,2,FALSE)&" ",FIND(" ",VLOOKUP($A12,COMPRADORES!$A:$D,2,FALSE)&" ")+1,99)),1)&".")),"")) | F12: =IF($B12="PAGADO",MID("ABCDEFGHIJ",INT(VALUE($A12)/100)+1,1)&"-"&$A12,"") | G12: =IF($B12="PAGADO","PAGADO",IF($B12="APARTADO",IF(NOT(ISNUMBER($C12)),"APARTADO",IF($C12<1,"APARTADO",IF(NOW()-$C12>1,"LIBRE","APARTADO"))),"LIBRE")) | H12: =IF($G12<>"APARTADO","",IF(NOT(ISNUMBER($C12)),"FALTA LA HORA",IF($C12<1,"FALTA LA FECHA",TEXT($C12+1,"dd/mm hh:mm"))))
A13: 011 | B13: LIBRE | E13: =IF($G13<>"PAGADO","",IFERROR(IF(VLOOKUP($A13,COMPRADORES!$A:$D,4,FALSE)="NO","Reservado",LEFT(VLOOKUP($A13,COMPRADORES!$A:$D,2,FALSE),3)&"***"&IF(TRIM(MID(VLOOKUP($A13,COMPRADORES!$A:$D,2,FALSE)&" ",FIND(" ",VLOOKUP($A13,COMPRADORES!$A:$D,2,FALSE)&" ")+1,99))="",""," "&LEFT(TRIM(MID(VLOOKUP($A13,COMPRADORES!$A:$D,2,FALSE)&" ",FIND(" ",VLOOKUP($A13,COMPRADORES!$A:$D,2,FALSE)&" ")+1,99)),1)&".")),"")) | F13: =IF($B13="PAGADO",MID("ABCDEFGHIJ",INT(VALUE($A13)/100)+1,1)&"-"&$A13,"") | G13: =IF($B13="PAGADO","PAGADO",IF($B13="APARTADO",IF(NOT(ISNUMBER($C13)),"APARTADO",IF($C13<1,"APARTADO",IF(NOW()-$C13>1,"LIBRE","APARTADO"))),"LIBRE")) | H13: =IF($G13<>"APARTADO","",IF(NOT(ISNUMBER($C13)),"FALTA LA HORA",IF($C13<1,"FALTA LA FECHA",TEXT($C13+1,"dd/mm hh:mm"))))
... A1001: 999 | B1001: LIBRE | E1001: =IF($G1001<>"PAGADO","",IFERROR(IF(VLOOKUP($A1001,COMPRADORES!$A:$D,4,FALSE)="NO","Reservado",LEFT(VLOOKUP($A1001,COMPRADORES!$A:$D,2,FALSE),3)&"***"&IF(TRIM(MID(VLOOKUP($A1001,COMPRADORES!$A:$D,2,FALSE)&" ",FIND(" ",VLOOKUP($A1001,COMPRADORES!$A:$D,2,FALSE)&" ")+1,99))="",""," "&LEFT(TRIM(MID(VLOOKUP($A1001,COMPRADORES!$A:$D,2,FALSE)&" ",FIND(" ",VLOOKUP($A1001,COMPRADORES!$A:$D,2,FALSE)&" ")+1,99)),1)&".")),"")) | F1001: =IF($B1001="PAGADO",MID("ABCDEFGHIJ",INT(VALUE($A1001)/100)+1,1)&"-"&$A1001,"") | G1001: =IF($B1001="PAGADO","PAGADO",IF($B1001="APARTADO",IF(NOT(ISNUMBER($C1001)),"APARTADO",IF($C1001<1,"APARTADO",IF(NOW()-$C1001>1,"LIBRE","APARTADO"))),"LIBRE")) | H1001: =IF($G1001<>"APARTADO","",IF(NOT(ISNUMBER($C1001)),"FALTA LA HORA",IF($C1001<1,"FALTA LA FECHA",TEXT($C1001+1,"dd/mm hh:mm"))))
A1003: NO ESCRIBAS EN LA COLUMNA E: es una fórmula. Los nombres van en la hoja COMPRADORES.
A1004: Si escribes un nombre en E, ese nombre completo QUEDA PUBLICADO en la web.
A1005: Columnas grises (E, F, G, H) = fórmulas, no se tocan. Solo escribes en B (estado), D (vendedor) y I (nota).

Sheet COMPRADORES
A1: NUMERO | B1: NOMBRE_COMPLETO | C1: TELEFONO | D1: SALE_PUBLICO | E1: QUIERE_TBW
A303: ESTA HOJA NO SE PUBLICA NI SE COMPARTE. Es la única con nombres completos y teléfonos.
A304: SALE_PUBLICO = NO -> ese número se ve en el tablero como «Reservado», sin nombre.
A305: QUIERE_TBW = SI -> dijo que SÍ quiere saber de The Ber Way (decisión 38). Vacío o NO = no se le escribe.

Sheet PAGOS
A1: FECHA_HORA | B1: NUMEROS | C1: CANTIDAD | D1: MONEDA | E1: MONTO | F1: MONTO_COP | G1: MEDIO | H1: VENDEDOR | I1: VERIFICADO_POR | J1: COMPROBANTE
F2: =IF($E2="","",IF($D2="NZD",$E2*NZ!$B$1,$E2))
F3: =IF($E3="","",IF($D3="NZD",$E3*NZ!$B$1,$E3))
F4: =IF($E4="","",IF($D4="NZD",$E4*NZ!$B$1,$E4))
F5: =IF($E5="","",IF($D5="NZD",$E5*NZ!$B$1,$E5))
F6: =IF($E6="","",IF($D6="NZD",$E6*NZ!$B$1,$E6))
F7: =IF($E7="","",IF($D7="NZD",$E7*NZ!$B$1,$E7))
F8: =IF($E8="","",IF($D8="NZD",$E8*NZ!$B$1,$E8))
F9: =IF($E9="","",IF($D9="NZD",$E9*NZ!$B$1,$E9))
F10: =IF($E10="","",IF($D10="NZD",$E10*NZ!$B$1,$E10))
F11: =IF($E11="","",IF($D11="NZD",$E11*NZ!$B$1,$E11))
F12: =IF($E12="","",IF($D12="NZD",$E12*NZ!$B$1,$E12))
F13: =IF($E13="","",IF($D13="NZD",$E13*NZ!$B$1,$E13))
... F401: =IF($E401="","",IF($D401="NZD",$E401*NZ!$B$1,$E401))
A403: Una fila entra acá SOLO cuando la plata ya se ve dentro de la app que recibe.
A404: Un pantallazo de «enviado» no es un pago: mientras tanto el número sigue APARTADO y puede vencerse.
A405: La columna MONTO_COP (gris) es fórmula: convierte los NZD con la tasa de NZ!B1. No se escribe a mano.

Sheet VENDEDORES
A1: CODIGO | B1: NOMBRE | C1: TIPO | D1: WHATSAPP | E1: LINK | F1: VENDIDOS | G1: APARTADOS | H1: COMISION | I1: ESTADO
A2: V01 | C2: VENDEDOR | E2: ="https://mega-rifa-fusa.vercel.app/?v=" & $A2 | F2: =COUNTIFS(NUMEROS!$D:$D,$A2,NUMEROS!$G:$G,"PAGADO") | G2: =COUNTIFS(NUMEROS!$D:$D,$A2,NUMEROS!$G:$G,"APARTADO") | H2: =IF($C2="TIENDA",$F2*600,0) | I2: ACTIVO
A3: V02 | C3: VENDEDOR | E3: ="https://mega-rifa-fusa.vercel.app/?v=" & $A3 | F3: =COUNTIFS(NUMEROS!$D:$D,$A3,NUMEROS!$G:$G,"PAGADO") | G3: =COUNTIFS(NUMEROS!$D:$D,$A3,NUMEROS!$G:$G,"APARTADO") | H3: =IF($C3="TIENDA",$F3*600,0) | I3: ACTIVO
A4: V03 | C4: VENDEDOR | E4: ="https://mega-rifa-fusa.vercel.app/?v=" & $A4 | F4: =COUNTIFS(NUMEROS!$D:$D,$A4,NUMEROS!$G:$G,"PAGADO") | G4: =COUNTIFS(NUMEROS!$D:$D,$A4,NUMEROS!$G:$G,"APARTADO") | H4: =IF($C4="TIENDA",$F4*600,0) | I4: ACTIVO
A5: V04 | C5: VENDEDOR | E5: ="https://mega-rifa-fusa.vercel.app/?v=" & $A5 | F5: =COUNTIFS(NUMEROS!$D:$D,$A5,NUMEROS!$G:$G,"PAGADO") | G5: =COUNTIFS(NUMEROS!$D:$D,$A5,NUMEROS!$G:$G,"APARTADO") | H5: =IF($C5="TIENDA",$F5*600,0) | I5: ACTIVO
A6: V05 | C6: VENDEDOR | E6: ="https://mega-rifa-fusa.vercel.app/?v=" & $A6 | F6: =COUNTIFS(NUMEROS!$D:$D,$A6,NUMEROS!$G:$G,"PAGADO") | G6: =COUNTIFS(NUMEROS!$D:$D,$A6,NUMEROS!$G:$G,"APARTADO") | H6: =IF($C6="TIENDA",$F6*600,0) | I6: ACTIVO
A7: V06 | C7: VENDEDOR | E7: ="https://mega-rifa-fusa.vercel.app/?v=" & $A7 | F7: =COUNTIFS(NUMEROS!$D:$D,$A7,NUMEROS!$G:$G,"PAGADO") | G7: =COUNTIFS(NUMEROS!$D:$D,$A7,NUMEROS!$G:$G,"APARTADO") | H7: =IF($C7="TIENDA",$F7*600,0) | I7: ACTIVO
A8: V07 | C8: VENDEDOR | E8: ="https://mega-rifa-fusa.vercel.app/?v=" & $A8 | F8: =COUNTIFS(NUMEROS!$D:$D,$A8,NUMEROS!$G:$G,"PAGADO") | G8: =COUNTIFS(NUMEROS!$D:$D,$A8,NUMEROS!$G:$G,"APARTADO") | H8: =IF($C8="TIENDA",$F8*600,0) | I8: ACTIVO
A9: V08 | C9: VENDEDOR | E9: ="https://mega-rifa-fusa.vercel.app/?v=" & $A9 | F9: =COUNTIFS(NUMEROS!$D:$D,$A9,NUMEROS!$G:$G,"PAGADO") | G9: =COUNTIFS(NUMEROS!$D:$D,$A9,NUMEROS!$G:$G,"APARTADO") | H9: =IF($C9="TIENDA",$F9*600,0) | I9: ACTIVO
A10: V09 | C10: VENDEDOR | E10: ="https://mega-rifa-fusa.vercel.app/?v=" & $A10 | F10: =COUNTIFS(NUMEROS!$D:$D,$A10,NUMEROS!$G:$G,"PAGADO") | G10: =COUNTIFS(NUMEROS!$D:$D,$A10,NUMEROS!$G:$G,"APARTADO") | H10: =IF($C10="TIENDA",$F10*600,0) | I10: ACTIVO
A11: V10 | C11: VENDEDOR | E11: ="https://mega-rifa-fusa.vercel.app/?v=" & $A11 | F11: =COUNTIFS(NUMEROS!$D:$D,$A11,NUMEROS!$G:$G,"PAGADO") | G11: =COUNTIFS(NUMEROS!$D:$D,$A11,NUMEROS!$G:$G,"APARTADO") | H11: =IF($C11="TIENDA",$F11*600,0) | I11: ACTIVO
A12: V11 | C12: VENDEDOR | E12: ="https://mega-rifa-fusa.vercel.app/?v=" & $A12 | F12: =COUNTIFS(NUMEROS!$D:$D,$A12,NUMEROS!$G:$G,"PAGADO") | G12: =COUNTIFS(NUMEROS!$D:$D,$A12,NUMEROS!$G:$G,"APARTADO") | H12: =IF($C12="TIENDA",$F12*600,0) | I12: ACTIVO
A13: V12 | C13: VENDEDOR | E13: ="https://mega-rifa-fusa.vercel.app/?v=" & $A13 | F13: =COUNTIFS(NUMEROS!$D:$D,$A13,NUMEROS!$G:$G,"PAGADO") | G13: =COUNTIFS(NUMEROS!$D:$D,$A13,NUMEROS!$G:$G,"APARTADO") | H13: =IF($C13="TIENDA",$F13*600,0) | I13: ACTIVO
... A16: T03 | C16: TIENDA | E16: ="https://mega-rifa-fusa.vercel.app/?v=" & $A16 | F16: =COUNTIFS(NUMEROS!$D:$D,$A16,NUMEROS!$G:$G,"PAGADO") | G16: =COUNTIFS(NUMEROS!$D:$D,$A16,NUMEROS!$G:$G,"APARTADO") | H16: =IF($C16="TIENDA",$F16*600,0) | I16: ACTIVO
A17: N01 | B17: Sofía | C17: NZ | E17: ="https://mega-rifa-fusa.vercel.app/?v=" & $A17 | F17: =COUNTIFS(NUMEROS!$D:$D,$A17,NUMEROS!$G:$G,"PAGADO") | G17: =COUNTIFS(NUMEROS!$D:$D,$A17,NUMEROS!$G:$G,"APARTADO") | H17: =IF($C17="TIENDA",$F17*600,0) | I17: ACTIVO
A18: N02 | B18: Reserva de Sofía | C18: NZ | E18: ="https://mega-rifa-fusa.vercel.app/?v=" & $A18 | F18: =COUNTIFS(NUMEROS!$D:$D,$A18,NUMEROS!$G:$G,"PAGADO") | G18: =COUNTIFS(NUMEROS!$D:$D,$A18,NUMEROS!$G:$G,"APARTADO") | H18: =IF($C18="TIENDA",$F18*600,0) | I18: ACTIVO
A19: SBG | B19: Santiago (venta directa) | C19: VENDEDOR | E19: ="https://mega-rifa-fusa.vercel.app/?v=" & $A19 | F19: =COUNTIFS(NUMEROS!$D:$D,$A19,NUMEROS!$G:$G,"PAGADO") | G19: =COUNTIFS(NUMEROS!$D:$D,$A19,NUMEROS!$G:$G,"APARTADO") | H19: =IF($C19="TIENDA",$F19*600,0) | I19: ACTIVO
A20: DIR | B20: Sin vendedor (llegó por el Canal o un Estado) | C20: VENDEDOR | E20: ="https://mega-rifa-fusa.vercel.app/?v=" & $A20 | F20: =COUNTIFS(NUMEROS!$D:$D,$A20,NUMEROS!$G:$G,"PAGADO") | G20: =COUNTIFS(NUMEROS!$D:$D,$A20,NUMEROS!$G:$G,"APARTADO") | H20: =IF($C20="TIENDA",$F20*600,0) | I20: ACTIVO
A22: ESTA HOJA NO SE PUBLICA: tiene nombres completos y teléfonos.
A23: La columna LINK ya trae el link real de cada vendedor. Solo llena NOMBRE y WHATSAPP.
A24: Columnas grises (LINK, VENDIDOS, APARTADOS, COMISION) = fórmulas, no se tocan.
A25: Puedes cambiar el código (V01) por el NOMBRE del vendedor, en MAYÚSCULAS, sin tildes ni espacios: ANGELICA, MARIAJOSE, JUANP. El link, los conteos y la lista del tablero se ajustan solos. Dos iguales: ANGELICA, ANGELICA2.

Sheet GASTOS
A1: FECHA | B1: CONCEPTO | C1: MONTO_COP | D1: CATEGORIA | E1: PAGADO
B2: Premio en efectivo | C2: 2000000 | D2: PREMIO | E2: NO
B3: Bono al vendedor estrella | C3: 100000 | D3: VENDEDOR | E3: NO
B4: Varios (impresiones, transporte) | C4: 50000 | D4: VARIOS | E4: NO

Sheet NZ
A1: TASA COP POR NZD | B1: 1843 | C1: Si se cambia, se anota en el registro de decisiones. PAGOS!F la lee de acá.
A3: FECHA | B3: NUMEROS | C3: NZD | D3: COP_EQUIV | E3: EN_CUENTA_DE_SOFIA | F3: NOTA
D4: =IF($C4="","",$C4*$B$1)
D5: =IF($C5="","",$C5*$B$1)
D6: =IF($C6="","",$C6*$B$1)
D7: =IF($C7="","",$C7*$B$1)
D8: =IF($C8="","",$C8*$B$1)
D9: =IF($C9="","",$C9*$B$1)
D10: =IF($C10="","",$C10*$B$1)
D11: =IF($C11="","",$C11*$B$1)
D12: =IF($C12="","",$C12*$B$1)
D13: =IF($C13="","",$C13*$B$1)
D14: =IF($C14="","",$C14*$B$1)
D15: =IF($C15="","",$C15*$B$1)
... D203: =IF($C203="","",$C203*$B$1)
A205: La plata de NZ no viaja. Se queda en la cuenta de Sofía y entra al total como equivalente.

Sheet RESUMEN
A1: MEGA RIFA FUSA — resumen
A3: Pagados | B3: =COUNTIF(NUMEROS!$G:$G,"PAGADO") | C3: Números con la plata ya verificada
A4: Apartados vivos | B4: =COUNTIF(NUMEROS!$G:$G,"APARTADO") | C4: Apartados que todavía no cumplen 24 h
A5: Libres | B5: =1000-$B$3-$B$4 | C5: Lo que de verdad queda
A6: Vencidos por recuperar | B6: =COUNTIFS(NUMEROS!$B:$B,"APARTADO",NUMEROS!$G:$G,"LIBRE") | C6: Se cayeron solos: hay que volver a ofrecerlos hoy
A7: Plata recibida (COP) | B7: =SUM(PAGOS!$F:$F) | C7: Todo lo que entró, con NZ convertido
A8: Gastos ya pagados | B8: =SUMIF(GASTOS!$E:$E,"SI",GASTOS!$C:$C) | C8: Solo los que dicen PAGADO = SI
A9: Comisión de tiendas | B9: =SUM(VENDEDORES!$H:$H) | C9: 10% = COP 600 por número de tienda
A10: NETO PROYECTADO | B10: =$B$7-2000000-100000-50000-$B$9 | C10: Lo que queda después del premio y los costos fijos
A11: Faltan para el piso (3M) | B11: =MAX(0,3000000-$B$10) | C11: Si llega a 0, la moto está asegurada
A12: Días para el sorteo | B12: =MAX(0,DATE(2026,12,5)-TODAY()) | C12: Hasta el sáb 5 de diciembre
A13: RITMO NECESARIO POR DÍA | B13: =IF($B$12>0,ROUNDUP((860-$B$3)/$B$12,0),0) | C13: Si pasa de 30, la campaña va atrasada
A15: El número que importa es el RITMO NECESARIO POR DÍA. Se mira cada domingo en el punto de control.

Sheet LEEME
A1: MEGA RIFA FUSA — cómo se usa este archivo
A3: Solo escribes en DOS momentos:
A4: 1. Alguien aparta un número -> en NUMEROS, columna B, pones APARTADO. La hora se pone sola.
A5: 2. Llega la plata y la ves en la app -> en COMPRADORES llenas UNA fila:
A6: número, nombre completo, teléfono, SALE_PUBLICO (SI/NO) y QUIERE_TBW (SI/NO).
A7: Al llenar esa fila, el número queda PAGADO solo, con su nombre acortado y su serial.
A9: Y anotas la plata en PAGOS (una fila por pago que entró).
A11: Lo demás se calcula solo. Las columnas grises son fórmulas: NO se tocan.
A12: La columna E de NUMEROS es la trampa: parece normal pero es fórmula y es la única pública.
A13: Si escribes un nombre ahí, ese nombre completo queda publicado en la web.
A15: Pestañas verdes = aquí se escribe (NUMEROS, COMPRADORES, PAGOS, VENDEDORES, GASTOS, NZ).
A16: Pestañas grises = solo se miran (HOY, RESUMEN, LEEME).
A17: Cada mañana mira la pestaña HOY. Cada domingo, la pestaña RESUMEN.
