Workbook

Sheet EMPIEZA
B2: MODELO FINANCIERO · EMPIEZA AQUÍ
B3: Escribe cuántos números llevas PAGADOS y mira las 3 cifras que importan.
B5: Números PAGADOS hoy | C5: 0 | D5: ↑ la única celda amarilla: escribe aquí
B8: Neto en el CASO MALO | C8: =$C$5*SUPUESTOS!$B$5-SUPUESTOS!$B$9-SUPUESTOS!$B$12-SUPUESTOS!$B$13 | D8: número vendido, sin tiendas ni NZ: lo más bajo que puede dar
B10: Faltan para el piso (3M) | C10: =MAX(0,ROUNDUP((SUPUESTOS!$B$25+SUPUESTOS!$B$9+SUPUESTOS!$B$12+SUPUESTOS!$B$13)/SUPUESTOS!$B$5,0)-$C$5) | D10: números PAGADOS que aún faltan para asegurar la moto
B12: ¿Ya llegó al piso? | C12: =IF($C$8>=SUPUESTOS!$B$25,"SÍ, la moto está asegurada","todavía no") | D12: el caso malo contra el piso de COP 3.000.000
B15: Para cambiar precios, premios o la mezcla: SUPUESTOS (celdas amarillas). Lo demás se calcula.
B16: Para ver el neto a distintos niveles de venta: ESCENARIOS. Los domingos: PUNTOS-CONTROL.

Sheet LEEME
B2: MODELO FINANCIERO - MEGA RIFA FUSA
B4: Para qué sirve
B5: Saber, en cualquier momento, cuántos números faltan para llegar al piso de COP 3.000.000 netos, y qué pasa con el neto si cambia la mezcla de ventas (directas, tiendas, Nueva Zelanda).
B7: Cómo se usa
B8: 0. La hoja EMPIEZA (la primera): escribe los números PAGADOS y te da el neto del caso malo y cuántos faltan para el piso. Panel rápido.
B9: 1. En la hoja SUPUESTOS, cambie solo las celdas con fondo AMARILLO. Todo lo demás se calcula solo.
B10: 2. La hoja ESCENARIOS muestra el neto para distintos totales de números vendidos, con la mezcla de SUPUESTOS.
B11: 3. La hoja CASOS-PRUEBA verifica que el modelo da los mismos números del plan maestro. Si alguna fila dice FALLA, el modelo quedó mal y no se puede confiar en él.
B12: 4. La hoja CAJAS lleva el control de la plata real: reserva del premio, efectivo, Nu y NZ.
B13: 5. La hoja VENDEDORES lleva los compradores distintos de cada vendedor (el umbral de 25 que da derecho al premio de COP 100.000).
B14: 6. La hoja PUNTOS-CONTROL compara lo vendido contra la meta de cada domingo.
B15: 7. La hoja REGLA-PREMIO compara qué pasa si el número de la Boyacá está vendido (se pagan los 2M) o no (premio de consolación), y el neto esperado (decisión 37).
... B25: Creado en la Sesión 1, el 2026-10-02.

Sheet SUPUESTOS
A1: SUPUESTOS - cambie solo las celdas amarillas
A3: Parámetro | B3: Valor | C3: Unidad | D3: Nota
A4: Total de números del tablero | B4: 1000 | C4: números | D4: 000-999. Decisión fija.
A5: Precio por número (Colombia) | B5: 6000 | C5: COP | D5: Decisión 6: COP 6.000 fijo, sin combo.
A6: Precio por número (Nueva Zelanda) | B6: 4 | C6: NZD | D6: Decisión 23: NZD 4 por número.
A7: Tasa de cambio COP por NZD | B7: 1843 | C7: COP/NZD | D7: Tasa media del mercado del 2026-10-02 (1.843,34). Actualizar antes de liquidar con NZ.
A8: Precio del número de NZ en pesos | B8: =B6*B7 | C8: COP | D8: Calculado. El número de NZ rinde más que el de Colombia.
A9: Premio al ganador (Colombia) | B9: 2000000 | C9: COP | D9: Decisiones 6 y 37: se paga completo si el número de la Boyacá está vendido. Si no, va el premio de consolación (hoja REGLA-PREMIO).
A10: Premio si el ganador está en NZ | B10: 1000 | C10: NZD | D10: Decisión 25.
A11: Mínimo garantizado si gana en NZ | B11: 1900000 | C11: COP | D11: Decisión 25: Sofía completa la diferencia si los NZD 1.000 valen menos.
A12: Premio al vendedor | B12: 100000 | C12: COP | D12: Decisión 9: solo si vendió a más de 25 personas distintas Y uno de sus compradores gana. El modelo lo cuenta siempre, por prudencia. Con la decisión 37, aplica también cuando va la consolación.
A13: Gastos varios | B13: 50000 | C13: COP | D13: Datos, imágenes, imprevistos. El formato es 100% digital, así que no hay impresión.
A14: Comisión de las tiendas aliadas | B14: 0.1 | C14: % | D14: Decisión 26: 10% por número. Cada número vendido en tienda deja COP 600 menos.
A15: Se contrata Tizumba? (0=no, 1=si) | B15: 0 | C15: 0 / 1 | D15: Decisión 16: se decide en el punto de control del dom 1 nov (31 oct - 1a semana de nov).
A16: Costo de Tizumba | B16: 100000 | C16: COP | D16: Estimado del plan maestro.
A17: Costo de Tizumba aplicado | B17: =B15*B16 | C17: COP | D17: Calculado.
A19: MEZCLA DE VENTAS (para ESCENARIOS)
A20: % de números vendidos en Nueva Zelanda | B20: 0.08 | C20: % | D20: Estimado del plan: 50-100 números de 1.000 (5-11%).
A21: % de números vendidos por tiendas | B21: 0.1 | C21: % | D21: Estimado: 1-3 tiendas x 20-40 números cada una.
A22: % de números vendidos directo (resto) | B22: =1-B20-B21 | C22: % | D22: Calculado. Son los que no pagan comisión.
A24: METAS
A25: Piso neto objetivo | B25: 3000000 | C25: COP | D25: Decisión 1. Es el mínimo para la moto más barata, y aun así deja los extras sin cubrir.
A26: Meta de números | B26: 900 | C26: números | D26: Plan maestro: el piso exige ~860-890, la meta da colchón.
A28: Amarillo = se edita. Crema = se calcula.

Sheet ESCENARIOS
A1: ESCENARIOS - neto segun numeros vendidos (mezcla de SUPUESTOS)
A2: La mezcla (% NZ y % tiendas) sale de SUPUESTOS. Cambie alla y toda la tabla se recalcula.
A4: Números vendidos | B4: % del tablero | C4: Núm. directos | D4: Núm. tiendas | E4: Núm. NZ | F4: Ingreso directo | G4: Ingreso tiendas | H4: Ingreso NZ | I4: INGRESO TOTAL | J4: Premio | K4: Premio vendedor | L4: Varios | M4: Comisión tiendas | N4: Tizumba | O4: COSTOS | P4: NETO | Q4: Llega al piso?
A5: 500 | B5: =A5/SUPUESTOS!$B$4 | C5: =ROUND(A5*(1-SUPUESTOS!$B$20-SUPUESTOS!$B$21),0) | D5: =ROUND(A5*SUPUESTOS!$B$21,0) | E5: =A5-C5-D5 | F5: =C5*SUPUESTOS!$B$5 | G5: =D5*SUPUESTOS!$B$5 | H5: =E5*SUPUESTOS!$B$8 | I5: =F5+G5+H5 | J5: =SUPUESTOS!$B$9 | K5: =SUPUESTOS!$B$12 | L5: =SUPUESTOS!$B$13 | M5: =G5*SUPUESTOS!$B$14 | N5: =SUPUESTOS!$B$17 | O5: =SUM(J5:N5) | P5: =I5-O5 | Q5: =IF(P5>=SUPUESTOS!$B$25,"SI","NO - faltan "&TEXT(ROUNDUP((SUPUESTOS!$B$25-P5)/SUPUESTOS!$B$5,0),"0")&" num.")
A6: 550 | B6: =A6/SUPUESTOS!$B$4 | C6: =ROUND(A6*(1-SUPUESTOS!$B$20-SUPUESTOS!$B$21),0) | D6: =ROUND(A6*SUPUESTOS!$B$21,0) | E6: =A6-C6-D6 | F6: =C6*SUPUESTOS!$B$5 | G6: =D6*SUPUESTOS!$B$5 | H6: =E6*SUPUESTOS!$B$8 | I6: =F6+G6+H6 | J6: =SUPUESTOS!$B$9 | K6: =SUPUESTOS!$B$12 | L6: =SUPUESTOS!$B$13 | M6: =G6*SUPUESTOS!$B$14 | N6: =SUPUESTOS!$B$17 | O6: =SUM(J6:N6) | P6: =I6-O6 | Q6: =IF(P6>=SUPUESTOS!$B$25,"SI","NO - faltan "&TEXT(ROUNDUP((SUPUESTOS!$B$25-P6)/SUPUESTOS!$B$5,0),"0")&" num.")
A7: 600 | B7: =A7/SUPUESTOS!$B$4 | C7: =ROUND(A7*(1-SUPUESTOS!$B$20-SUPUESTOS!$B$21),0) | D7: =ROUND(A7*SUPUESTOS!$B$21,0) | E7: =A7-C7-D7 | F7: =C7*SUPUESTOS!$B$5 | G7: =D7*SUPUESTOS!$B$5 | H7: =E7*SUPUESTOS!$B$8 | I7: =F7+G7+H7 | J7: =SUPUESTOS!$B$9 | K7: =SUPUESTOS!$B$12 | L7: =SUPUESTOS!$B$13 | M7: =G7*SUPUESTOS!$B$14 | N7: =SUPUESTOS!$B$17 | O7: =SUM(J7:N7) | P7: =I7-O7 | Q7: =IF(P7>=SUPUESTOS!$B$25,"SI","NO - faltan "&TEXT(ROUNDUP((SUPUESTOS!$B$25-P7)/SUPUESTOS!$B$5,0),"0")&" num.")
A8: 650 | B8: =A8/SUPUESTOS!$B$4 | C8: =ROUND(A8*(1-SUPUESTOS!$B$20-SUPUESTOS!$B$21),0) | D8: =ROUND(A8*SUPUESTOS!$B$21,0) | E8: =A8-C8-D8 | F8: =C8*SUPUESTOS!$B$5 | G8: =D8*SUPUESTOS!$B$5 | H8: =E8*SUPUESTOS!$B$8 | I8: =F8+G8+H8 | J8: =SUPUESTOS!$B$9 | K8: =SUPUESTOS!$B$12 | L8: =SUPUESTOS!$B$13 | M8: =G8*SUPUESTOS!$B$14 | N8: =SUPUESTOS!$B$17 | O8: =SUM(J8:N8) | P8: =I8-O8 | Q8: =IF(P8>=SUPUESTOS!$B$25,"SI","NO - faltan "&TEXT(ROUNDUP((SUPUESTOS!$B$25-P8)/SUPUESTOS!$B$5,0),"0")&" num.")
A9: 700 | B9: =A9/SUPUESTOS!$B$4 | C9: =ROUND(A9*(1-SUPUESTOS!$B$20-SUPUESTOS!$B$21),0) | D9: =ROUND(A9*SUPUESTOS!$B$21,0) | E9: =A9-C9-D9 | F9: =C9*SUPUESTOS!$B$5 | G9: =D9*SUPUESTOS!$B$5 | H9: =E9*SUPUESTOS!$B$8 | I9: =F9+G9+H9 | J9: =SUPUESTOS!$B$9 | K9: =SUPUESTOS!$B$12 | L9: =SUPUESTOS!$B$13 | M9: =G9*SUPUESTOS!$B$14 | N9: =SUPUESTOS!$B$17 | O9: =SUM(J9:N9) | P9: =I9-O9 | Q9: =IF(P9>=SUPUESTOS!$B$25,"SI","NO - faltan "&TEXT(ROUNDUP((SUPUESTOS!$B$25-P9)/SUPUESTOS!$B$5,0),"0")&" num.")
A10: 750 | B10: =A10/SUPUESTOS!$B$4 | C10: =ROUND(A10*(1-SUPUESTOS!$B$20-SUPUESTOS!$B$21),0) | D10: =ROUND(A10*SUPUESTOS!$B$21,0) | E10: =A10-C10-D10 | F10: =C10*SUPUESTOS!$B$5 | G10: =D10*SUPUESTOS!$B$5 | H10: =E10*SUPUESTOS!$B$8 | I10: =F10+G10+H10 | J10: =SUPUESTOS!$B$9 | K10: =SUPUESTOS!$B$12 | L10: =SUPUESTOS!$B$13 | M10: =G10*SUPUESTOS!$B$14 | N10: =SUPUESTOS!$B$17 | O10: =SUM(J10:N10) | P10: =I10-O10 | Q10: =IF(P10>=SUPUESTOS!$B$25,"SI","NO - faltan "&TEXT(ROUNDUP((SUPUESTOS!$B$25-P10)/SUPUESTOS!$B$5,0),"0")&" num.")
A11: 800 | B11: =A11/SUPUESTOS!$B$4 | C11: =ROUND(A11*(1-SUPUESTOS!$B$20-SUPUESTOS!$B$21),0) | D11: =ROUND(A11*SUPUESTOS!$B$21,0) | E11: =A11-C11-D11 | F11: =C11*SUPUESTOS!$B$5 | G11: =D11*SUPUESTOS!$B$5 | H11: =E11*SUPUESTOS!$B$8 | I11: =F11+G11+H11 | J11: =SUPUESTOS!$B$9 | K11: =SUPUESTOS!$B$12 | L11: =SUPUESTOS!$B$13 | M11: =G11*SUPUESTOS!$B$14 | N11: =SUPUESTOS!$B$17 | O11: =SUM(J11:N11) | P11: =I11-O11 | Q11: =IF(P11>=SUPUESTOS!$B$25,"SI","NO - faltan "&TEXT(ROUNDUP((SUPUESTOS!$B$25-P11)/SUPUESTOS!$B$5,0),"0")&" num.")
A12: 850 | B12: =A12/SUPUESTOS!$B$4 | C12: =ROUND(A12*(1-SUPUESTOS!$B$20-SUPUESTOS!$B$21),0) | D12: =ROUND(A12*SUPUESTOS!$B$21,0) | E12: =A12-C12-D12 | F12: =C12*SUPUESTOS!$B$5 | G12: =D12*SUPUESTOS!$B$5 | H12: =E12*SUPUESTOS!$B$8 | I12: =F12+G12+H12 | J12: =SUPUESTOS!$B$9 | K12: =SUPUESTOS!$B$12 | L12: =SUPUESTOS!$B$13 | M12: =G12*SUPUESTOS!$B$14 | N12: =SUPUESTOS!$B$17 | O12: =SUM(J12:N12) | P12: =I12-O12 | Q12: =IF(P12>=SUPUESTOS!$B$25,"SI","NO - faltan "&TEXT(ROUNDUP((SUPUESTOS!$B$25-P12)/SUPUESTOS!$B$5,0),"0")&" num.")
A13: 859 | B13: =A13/SUPUESTOS!$B$4 | C13: =ROUND(A13*(1-SUPUESTOS!$B$20-SUPUESTOS!$B$21),0) | D13: =ROUND(A13*SUPUESTOS!$B$21,0) | E13: =A13-C13-D13 | F13: =C13*SUPUESTOS!$B$5 | G13: =D13*SUPUESTOS!$B$5 | H13: =E13*SUPUESTOS!$B$8 | I13: =F13+G13+H13 | J13: =SUPUESTOS!$B$9 | K13: =SUPUESTOS!$B$12 | L13: =SUPUESTOS!$B$13 | M13: =G13*SUPUESTOS!$B$14 | N13: =SUPUESTOS!$B$17 | O13: =SUM(J13:N13) | P13: =I13-O13 | Q13: =IF(P13>=SUPUESTOS!$B$25,"SI","NO - faltan "&TEXT(ROUNDUP((SUPUESTOS!$B$25-P13)/SUPUESTOS!$B$5,0),"0")&" num.")
A14: 867 | B14: =A14/SUPUESTOS!$B$4 | C14: =ROUND(A14*(1-SUPUESTOS!$B$20-SUPUESTOS!$B$21),0) | D14: =ROUND(A14*SUPUESTOS!$B$21,0) | E14: =A14-C14-D14 | F14: =C14*SUPUESTOS!$B$5 | G14: =D14*SUPUESTOS!$B$5 | H14: =E14*SUPUESTOS!$B$8 | I14: =F14+G14+H14 | J14: =SUPUESTOS!$B$9 | K14: =SUPUESTOS!$B$12 | L14: =SUPUESTOS!$B$13 | M14: =G14*SUPUESTOS!$B$14 | N14: =SUPUESTOS!$B$17 | O14: =SUM(J14:N14) | P14: =I14-O14 | Q14: =IF(P14>=SUPUESTOS!$B$25,"SI","NO - faltan "&TEXT(ROUNDUP((SUPUESTOS!$B$25-P14)/SUPUESTOS!$B$5,0),"0")&" num.")
A15: 890 | B15: =A15/SUPUESTOS!$B$4 | C15: =ROUND(A15*(1-SUPUESTOS!$B$20-SUPUESTOS!$B$21),0) | D15: =ROUND(A15*SUPUESTOS!$B$21,0) | E15: =A15-C15-D15 | F15: =C15*SUPUESTOS!$B$5 | G15: =D15*SUPUESTOS!$B$5 | H15: =E15*SUPUESTOS!$B$8 | I15: =F15+G15+H15 | J15: =SUPUESTOS!$B$9 | K15: =SUPUESTOS!$B$12 | L15: =SUPUESTOS!$B$13 | M15: =G15*SUPUESTOS!$B$14 | N15: =SUPUESTOS!$B$17 | O15: =SUM(J15:N15) | P15: =I15-O15 | Q15: =IF(P15>=SUPUESTOS!$B$25,"SI","NO - faltan "&TEXT(ROUNDUP((SUPUESTOS!$B$25-P15)/SUPUESTOS!$B$5,0),"0")&" num.")
A16: 900 | B16: =A16/SUPUESTOS!$B$4 | C16: =ROUND(A16*(1-SUPUESTOS!$B$20-SUPUESTOS!$B$21),0) | D16: =ROUND(A16*SUPUESTOS!$B$21,0) | E16: =A16-C16-D16 | F16: =C16*SUPUESTOS!$B$5 | G16: =D16*SUPUESTOS!$B$5 | H16: =E16*SUPUESTOS!$B$8 | I16: =F16+G16+H16 | J16: =SUPUESTOS!$B$9 | K16: =SUPUESTOS!$B$12 | L16: =SUPUESTOS!$B$13 | M16: =G16*SUPUESTOS!$B$14 | N16: =SUPUESTOS!$B$17 | O16: =SUM(J16:N16) | P16: =I16-O16 | Q16: =IF(P16>=SUPUESTOS!$B$25,"SI","NO - faltan "&TEXT(ROUNDUP((SUPUESTOS!$B$25-P16)/SUPUESTOS!$B$5,0),"0")&" num.")
... A18: 1000 | B18: =A18/SUPUESTOS!$B$4 | C18: =ROUND(A18*(1-SUPUESTOS!$B$20-SUPUESTOS!$B$21),0) | D18: =ROUND(A18*SUPUESTOS!$B$21,0) | E18: =A18-C18-D18 | F18: =C18*SUPUESTOS!$B$5 | G18: =D18*SUPUESTOS!$B$5 | H18: =E18*SUPUESTOS!$B$8 | I18: =F18+G18+H18 | J18: =SUPUESTOS!$B$9 | K18: =SUPUESTOS!$B$12 | L18: =SUPUESTOS!$B$13 | M18: =G18*SUPUESTOS!$B$14 | N18: =SUPUESTOS!$B$17 | O18: =SUM(J18:N18) | P18: =I18-O18 | Q18: =IF(P18>=SUPUESTOS!$B$25,"SI","NO - faltan "&TEXT(ROUNDUP((SUPUESTOS!$B$25-P18)/SUPUESTOS!$B$5,0),"0")&" num.")
A20: Filas resaltadas: 859 = piso del plan sin ventas de tiendas | 867 = punto de equilibrio que calculo la investigacion a 0% de comision | 890 = tope del rango del piso | 900 = meta.
A21: Con la mezcla de SUPUESTOS el neto cambia: los numeros de NZ rinden mas (NZD 4 = COP 7.372) y los de tienda rinden menos (COP 5.400 despues de la comision).
A22: Esta hoja muestra el caso en que el número de la Boyacá está VENDIDO (se pagan los 2M), que es el caso malo. El caso sin vender y el neto esperado están en REGLA-PREMIO (decisión 37).
A23: CALCULADORA: cuantos numeros faltan?
A24: Números PAGADO hoy | B24: 0
A25: Neto con lo de hoy | B25: =ROUND(B24*(1-SUPUESTOS!$B$20-SUPUESTOS!$B$21),0)*SUPUESTOS!$B$5+ROUND(B24*SUPUESTOS!$B$21,0)*SUPUESTOS!$B$5*(1-SUPUESTOS!$B$14)+(B24-ROUND(B24*(1-SUPUESTOS!$B$20-SUPUESTOS!$B$21),0)-ROUND(B24*SUPUESTOS!$B$21,0))*SUPUESTOS!$B$8-SUPUESTOS!$B$9-SUPUESTOS!$B$12-SUPUESTOS!$B$13-SUPUESTOS!$B$17
A26: Falta para el piso | B26: =MAX(0,SUPUESTOS!$B$25-B25)
A27: Números que faltan (directos) | B27: =ROUNDUP(B26/SUPUESTOS!$B$5,0)
A28: Días que faltan para el cierre | B28: =MAX(0,DATE(2026,12,5)-TODAY())
A29: Números por día que exige | B29: =IF(B28=0,0,ROUNDUP(B27/B28,1))

Sheet REGLA-PREMIO
A1: REGLA DEL PREMIO - decisión 37: si el número de la Boyacá no se vendió, va un premio de consolación
A2: Si las últimas 3 cifras del premio mayor de la Boyacá caen en un número PAGADO, se pagan los COP 2.000.000. Si caen en uno sin vender, no hay premio de 2M: el siguiente número vendido se lleva el premio de consolación. La probabilidad de que el número esté vendido es: vendidos / 1.000.
A4: Premio de consolación | B4: 210000 | C4: Decidido el 2026-10-09 (decisión 41): el whisky se compra DESPUÉS del sorteo, solo si se activa la consolación. No se aparta plata: si nadie compró el número ganador, de la reserva de 2M (que no se paga) salen los 210k. La captura del 8 oct (Buchanan's Master 750 ml, COP 210.000, Éxito) es solo referencia de precio.
A5: Premio al vendedor si va la consolación | B5: 100000 | C5: Decidido el 2026-10-08: los COP 100.000 al vendedor aplican también cuando va la consolación (si vendió a más de 25 personas distintas y uno de sus compradores gana).
A7: Números vendidos | B7: Prob. de que el número esté vendido | C7: INGRESO TOTAL | D7: Varios + comisión tiendas + Tizumba | E7: NETO si se vendió (paga 2M) = caso malo | F7: NETO si no se vendió (consolación) | G7: NETO ESPERADO | H7: ¿El caso malo llega al piso?
A8: 300 | B8: =A8/SUPUESTOS!$B$4 | C8: =ROUND(A8*(1-SUPUESTOS!$B$20-SUPUESTOS!$B$21),0)*SUPUESTOS!$B$5+ROUND(A8*SUPUESTOS!$B$21,0)*SUPUESTOS!$B$5+(A8-ROUND(A8*(1-SUPUESTOS!$B$20-SUPUESTOS!$B$21),0)-ROUND(A8*SUPUESTOS!$B$21,0))*SUPUESTOS!$B$8 | D8: =SUPUESTOS!$B$13+ROUND(A8*SUPUESTOS!$B$21,0)*SUPUESTOS!$B$5*SUPUESTOS!$B$14+SUPUESTOS!$B$17 | E8: =C8-D8-SUPUESTOS!$B$9-SUPUESTOS!$B$12 | F8: =C8-D8-$B$4-$B$5 | G8: =B8*E8+(1-B8)*F8 | H8: =IF(E8>=SUPUESTOS!$B$25,"SI","NO")
A9: 360 | B9: =A9/SUPUESTOS!$B$4 | C9: =ROUND(A9*(1-SUPUESTOS!$B$20-SUPUESTOS!$B$21),0)*SUPUESTOS!$B$5+ROUND(A9*SUPUESTOS!$B$21,0)*SUPUESTOS!$B$5+(A9-ROUND(A9*(1-SUPUESTOS!$B$20-SUPUESTOS!$B$21),0)-ROUND(A9*SUPUESTOS!$B$21,0))*SUPUESTOS!$B$8 | D9: =SUPUESTOS!$B$13+ROUND(A9*SUPUESTOS!$B$21,0)*SUPUESTOS!$B$5*SUPUESTOS!$B$14+SUPUESTOS!$B$17 | E9: =C9-D9-SUPUESTOS!$B$9-SUPUESTOS!$B$12 | F9: =C9-D9-$B$4-$B$5 | G9: =B9*E9+(1-B9)*F9 | H9: =IF(E9>=SUPUESTOS!$B$25,"SI","NO")
A10: 400 | B10: =A10/SUPUESTOS!$B$4 | C10: =ROUND(A10*(1-SUPUESTOS!$B$20-SUPUESTOS!$B$21),0)*SUPUESTOS!$B$5+ROUND(A10*SUPUESTOS!$B$21,0)*SUPUESTOS!$B$5+(A10-ROUND(A10*(1-SUPUESTOS!$B$20-SUPUESTOS!$B$21),0)-ROUND(A10*SUPUESTOS!$B$21,0))*SUPUESTOS!$B$8 | D10: =SUPUESTOS!$B$13+ROUND(A10*SUPUESTOS!$B$21,0)*SUPUESTOS!$B$5*SUPUESTOS!$B$14+SUPUESTOS!$B$17 | E10: =C10-D10-SUPUESTOS!$B$9-SUPUESTOS!$B$12 | F10: =C10-D10-$B$4-$B$5 | G10: =B10*E10+(1-B10)*F10 | H10: =IF(E10>=SUPUESTOS!$B$25,"SI","NO")
A11: 500 | B11: =A11/SUPUESTOS!$B$4 | C11: =ROUND(A11*(1-SUPUESTOS!$B$20-SUPUESTOS!$B$21),0)*SUPUESTOS!$B$5+ROUND(A11*SUPUESTOS!$B$21,0)*SUPUESTOS!$B$5+(A11-ROUND(A11*(1-SUPUESTOS!$B$20-SUPUESTOS!$B$21),0)-ROUND(A11*SUPUESTOS!$B$21,0))*SUPUESTOS!$B$8 | D11: =SUPUESTOS!$B$13+ROUND(A11*SUPUESTOS!$B$21,0)*SUPUESTOS!$B$5*SUPUESTOS!$B$14+SUPUESTOS!$B$17 | E11: =C11-D11-SUPUESTOS!$B$9-SUPUESTOS!$B$12 | F11: =C11-D11-$B$4-$B$5 | G11: =B11*E11+(1-B11)*F11 | H11: =IF(E11>=SUPUESTOS!$B$25,"SI","NO")
A12: 600 | B12: =A12/SUPUESTOS!$B$4 | C12: =ROUND(A12*(1-SUPUESTOS!$B$20-SUPUESTOS!$B$21),0)*SUPUESTOS!$B$5+ROUND(A12*SUPUESTOS!$B$21,0)*SUPUESTOS!$B$5+(A12-ROUND(A12*(1-SUPUESTOS!$B$20-SUPUESTOS!$B$21),0)-ROUND(A12*SUPUESTOS!$B$21,0))*SUPUESTOS!$B$8 | D12: =SUPUESTOS!$B$13+ROUND(A12*SUPUESTOS!$B$21,0)*SUPUESTOS!$B$5*SUPUESTOS!$B$14+SUPUESTOS!$B$17 | E12: =C12-D12-SUPUESTOS!$B$9-SUPUESTOS!$B$12 | F12: =C12-D12-$B$4-$B$5 | G12: =B12*E12+(1-B12)*F12 | H12: =IF(E12>=SUPUESTOS!$B$25,"SI","NO")
A13: 650 | B13: =A13/SUPUESTOS!$B$4 | C13: =ROUND(A13*(1-SUPUESTOS!$B$20-SUPUESTOS!$B$21),0)*SUPUESTOS!$B$5+ROUND(A13*SUPUESTOS!$B$21,0)*SUPUESTOS!$B$5+(A13-ROUND(A13*(1-SUPUESTOS!$B$20-SUPUESTOS!$B$21),0)-ROUND(A13*SUPUESTOS!$B$21,0))*SUPUESTOS!$B$8 | D13: =SUPUESTOS!$B$13+ROUND(A13*SUPUESTOS!$B$21,0)*SUPUESTOS!$B$5*SUPUESTOS!$B$14+SUPUESTOS!$B$17 | E13: =C13-D13-SUPUESTOS!$B$9-SUPUESTOS!$B$12 | F13: =C13-D13-$B$4-$B$5 | G13: =B13*E13+(1-B13)*F13 | H13: =IF(E13>=SUPUESTOS!$B$25,"SI","NO")
A14: 700 | B14: =A14/SUPUESTOS!$B$4 | C14: =ROUND(A14*(1-SUPUESTOS!$B$20-SUPUESTOS!$B$21),0)*SUPUESTOS!$B$5+ROUND(A14*SUPUESTOS!$B$21,0)*SUPUESTOS!$B$5+(A14-ROUND(A14*(1-SUPUESTOS!$B$20-SUPUESTOS!$B$21),0)-ROUND(A14*SUPUESTOS!$B$21,0))*SUPUESTOS!$B$8 | D14: =SUPUESTOS!$B$13+ROUND(A14*SUPUESTOS!$B$21,0)*SUPUESTOS!$B$5*SUPUESTOS!$B$14+SUPUESTOS!$B$17 | E14: =C14-D14-SUPUESTOS!$B$9-SUPUESTOS!$B$12 | F14: =C14-D14-$B$4-$B$5 | G14: =B14*E14+(1-B14)*F14 | H14: =IF(E14>=SUPUESTOS!$B$25,"SI","NO")
A15: 750 | B15: =A15/SUPUESTOS!$B$4 | C15: =ROUND(A15*(1-SUPUESTOS!$B$20-SUPUESTOS!$B$21),0)*SUPUESTOS!$B$5+ROUND(A15*SUPUESTOS!$B$21,0)*SUPUESTOS!$B$5+(A15-ROUND(A15*(1-SUPUESTOS!$B$20-SUPUESTOS!$B$21),0)-ROUND(A15*SUPUESTOS!$B$21,0))*SUPUESTOS!$B$8 | D15: =SUPUESTOS!$B$13+ROUND(A15*SUPUESTOS!$B$21,0)*SUPUESTOS!$B$5*SUPUESTOS!$B$14+SUPUESTOS!$B$17 | E15: =C15-D15-SUPUESTOS!$B$9-SUPUESTOS!$B$12 | F15: =C15-D15-$B$4-$B$5 | G15: =B15*E15+(1-B15)*F15 | H15: =IF(E15>=SUPUESTOS!$B$25,"SI","NO")
A16: 800 | B16: =A16/SUPUESTOS!$B$4 | C16: =ROUND(A16*(1-SUPUESTOS!$B$20-SUPUESTOS!$B$21),0)*SUPUESTOS!$B$5+ROUND(A16*SUPUESTOS!$B$21,0)*SUPUESTOS!$B$5+(A16-ROUND(A16*(1-SUPUESTOS!$B$20-SUPUESTOS!$B$21),0)-ROUND(A16*SUPUESTOS!$B$21,0))*SUPUESTOS!$B$8 | D16: =SUPUESTOS!$B$13+ROUND(A16*SUPUESTOS!$B$21,0)*SUPUESTOS!$B$5*SUPUESTOS!$B$14+SUPUESTOS!$B$17 | E16: =C16-D16-SUPUESTOS!$B$9-SUPUESTOS!$B$12 | F16: =C16-D16-$B$4-$B$5 | G16: =B16*E16+(1-B16)*F16 | H16: =IF(E16>=SUPUESTOS!$B$25,"SI","NO")
A17: 860 | B17: =A17/SUPUESTOS!$B$4 | C17: =ROUND(A17*(1-SUPUESTOS!$B$20-SUPUESTOS!$B$21),0)*SUPUESTOS!$B$5+ROUND(A17*SUPUESTOS!$B$21,0)*SUPUESTOS!$B$5+(A17-ROUND(A17*(1-SUPUESTOS!$B$20-SUPUESTOS!$B$21),0)-ROUND(A17*SUPUESTOS!$B$21,0))*SUPUESTOS!$B$8 | D17: =SUPUESTOS!$B$13+ROUND(A17*SUPUESTOS!$B$21,0)*SUPUESTOS!$B$5*SUPUESTOS!$B$14+SUPUESTOS!$B$17 | E17: =C17-D17-SUPUESTOS!$B$9-SUPUESTOS!$B$12 | F17: =C17-D17-$B$4-$B$5 | G17: =B17*E17+(1-B17)*F17 | H17: =IF(E17>=SUPUESTOS!$B$25,"SI","NO")
A18: 900 | B18: =A18/SUPUESTOS!$B$4 | C18: =ROUND(A18*(1-SUPUESTOS!$B$20-SUPUESTOS!$B$21),0)*SUPUESTOS!$B$5+ROUND(A18*SUPUESTOS!$B$21,0)*SUPUESTOS!$B$5+(A18-ROUND(A18*(1-SUPUESTOS!$B$20-SUPUESTOS!$B$21),0)-ROUND(A18*SUPUESTOS!$B$21,0))*SUPUESTOS!$B$8 | D18: =SUPUESTOS!$B$13+ROUND(A18*SUPUESTOS!$B$21,0)*SUPUESTOS!$B$5*SUPUESTOS!$B$14+SUPUESTOS!$B$17 | E18: =C18-D18-SUPUESTOS!$B$9-SUPUESTOS!$B$12 | F18: =C18-D18-$B$4-$B$5 | G18: =B18*E18+(1-B18)*F18 | H18: =IF(E18>=SUPUESTOS!$B$25,"SI","NO")
A19: 1000 | B19: =A19/SUPUESTOS!$B$4 | C19: =ROUND(A19*(1-SUPUESTOS!$B$20-SUPUESTOS!$B$21),0)*SUPUESTOS!$B$5+ROUND(A19*SUPUESTOS!$B$21,0)*SUPUESTOS!$B$5+(A19-ROUND(A19*(1-SUPUESTOS!$B$20-SUPUESTOS!$B$21),0)-ROUND(A19*SUPUESTOS!$B$21,0))*SUPUESTOS!$B$8 | D19: =SUPUESTOS!$B$13+ROUND(A19*SUPUESTOS!$B$21,0)*SUPUESTOS!$B$5*SUPUESTOS!$B$14+SUPUESTOS!$B$17 | E19: =C19-D19-SUPUESTOS!$B$9-SUPUESTOS!$B$12 | F19: =C19-D19-$B$4-$B$5 | G19: =B19*E19+(1-B19)*F19 | H19: =IF(E19>=SUPUESTOS!$B$25,"SI","NO")
A21: Cómo leerla: la regla NO cambia el caso malo. Si el número está vendido, el neto es exactamente el mismo de la regla anterior (columna E = ESCENARIOS!P). Lo que agrega es una probabilidad (1 - columna B) de quedarse con la columna F.
A22: Para tener COP 3.000.000 seguros siguen haciendo falta ~860 vendidos (columna H). Pérdida solo si se venden menos de ~360 Y el número cae en uno vendido.
A23: Filas resaltadas: 650 = centro estimado si el sorteo fuera el 21 nov · 800 = centro estimado si fuera el 19 dic · 860 = piso. Con el sorteo del 5 dic (decidido el 2026-10-06) el centro estimado es ~700 (fila 700). Las cifras usan la mezcla de SUPUESTOS.
A24: Fuente: 02_Decisiones/registro-de-decisiones.md (decisión 37) y 02_Decisiones/analisis-premio-y-tiempo.md. Creada el 2026-10-06.

Sheet CASOS-PRUEBA
A1: CASOS DE PRUEBA - verificacion del modelo (plan maestro, seccion Verificacion)
A2: Si alguna fila dice FALLA, el modelo quedo mal y no se puede usar para decidir nada.
A4: Caso | B4: Resultado del modelo | C4: Esperado | D4: Diferencia | E4: Veredicto | F4: Cómo se calcula
A5: 859 vendidos, sin ventas de tiendas, sin NZ -> neto >= COP 3.000.000 | B5: =859*SUPUESTOS!$B$5-SUPUESTOS!$B$9-SUPUESTOS!$B$12-SUPUESTOS!$B$13 | C5: 3004000 | D5: =B5-C5 | E5: =IF(AND(B5>=SUPUESTOS!$B$25,ABS(D5)<1),"PASA","FALLA") | F5: 859 x 6.000 = 5.154.000, menos premio 2.000.000, premio del vendedor 100.000 y varios 50.000.
A6: 700 vendidos, sin ventas de tiendas, sin NZ -> aprox. COP 2.050.000 | B6: =700*SUPUESTOS!$B$5-SUPUESTOS!$B$9-SUPUESTOS!$B$12-SUPUESTOS!$B$13 | C6: 2050000 | D6: =B6-C6 | E6: =IF(ABS(D6)<1,"PASA","FALLA") | F6: 700 x 6.000 = 4.200.000, menos 2.150.000 de costos fijos.
A7: 100 números de NZ se convierten a la tasa escogida | B7: =100*SUPUESTOS!$B$6*SUPUESTOS!$B$7 | C7: 737200 | D7: =B7-C7 | E7: =IF(ABS(D7)<1,"PASA","FALLA") | F7: 100 x NZD 4 x 1.843 = COP 737.200 (contra 600.000 si fueran al precio colombiano).
A8: Un número de NZ en pesos (aprox. COP 7.370) | B8: =SUPUESTOS!$B$6*SUPUESTOS!$B$7 | C8: 7372 | D8: =B8-C8 | E8: =IF(ABS(D8)<1,"PASA","FALLA") | F8: NZD 4 x 1.843. El plan dice aprox. 7.370; el modelo da 7.372 con la tasa redondeada.
A9: Premio de NZD 1.000 en pesos vs minimo de COP 1.900.000 | B9: =SUPUESTOS!$B$10*SUPUESTOS!$B$7 | C9: 1843000 | D9: =B9-C9 | E9: =IF(ABS(D9)<1,IF(B9<SUPUESTOS!$B$11,"PASA (confirma que falta completar)","PASA"),"FALLA") | F9: NZD 1.000 x 1.843 = 1.843.000, POR DEBAJO del minimo de 1.900.000: Sofia completa ~NZD 31 (decision 25).
A10: 650 vendidos, número de la Boyacá VENDIDO (paga 2M), sin tiendas ni NZ -> COP 1.750.000 | B10: =650*SUPUESTOS!$B$5-SUPUESTOS!$B$9-SUPUESTOS!$B$12-SUPUESTOS!$B$13 | C10: 1750000 | D10: =B10-C10 | E10: =IF(ABS(D10)<1,"PASA","FALLA") | F10: Decisión 37, caso malo: 650 x 6.000 = 3.900.000, menos premio 2.000.000, premio del vendedor 100.000 y varios 50.000. Igual que con la regla anterior.
A11: 650 vendidos, número SIN VENDER (consolación), sin tiendas ni NZ -> COP 3.540.000 | B11: =650*SUPUESTOS!$B$5-'REGLA-PREMIO'!$B$4-'REGLA-PREMIO'!$B$5-SUPUESTOS!$B$13 | C11: 3540000 | D11: =B11-C11 | E11: =IF(ABS(D11)<1,"PASA","FALLA") | F11: 3.900.000 menos consolación 210.000, premio del vendedor 100.000 y varios 50.000 (decisión 37: el vendedor cobra también con la consolación).
A12: Neto ESPERADO con 800 vendidos, sin tiendas ni NZ -> COP 3.008.000 | B12: =0.8*(800*SUPUESTOS!$B$5-SUPUESTOS!$B$9-SUPUESTOS!$B$12-SUPUESTOS!$B$13)+0.2*(800*SUPUESTOS!$B$5-'REGLA-PREMIO'!$B$4-'REGLA-PREMIO'!$B$5-SUPUESTOS!$B$13) | C12: 3008000 | D12: =B12-C12 | E12: =IF(ABS(D12)<1,"PASA","FALLA") | F12: 80% de probabilidad de pagar los 2M (neto 2.650.000) y 20% de consolación (neto 4.440.000).
A13: REGLA-PREMIO y ESCENARIOS dan el mismo caso malo con 650 vendidos (con la mezcla) | B13: ='REGLA-PREMIO'!E13-ESCENARIOS!P8 | C13: 0 | D13: =B13-C13 | E13: =IF(ABS(D13)<1,"PASA","FALLA") | F13: Si el número está vendido, la regla nueva tiene que dar exactamente lo mismo que la anterior. Diferencia esperada: 0.
A15: RESULTADO GENERAL | B15: =IF(COUNTIF(E5:E13,"FALLA*")>0,"HAY FALLAS - revisar","TODOS PASAN")
A17: Nota sobre el premio al vendedor: en los casos 1 y 2 se cuenta siempre, aunque la decision 9 solo lo paga si el vendedor del numero ganador le vendio a mas de 25 personas distintas. Contarlo siempre es el supuesto prudente, y es el que reproduce las cifras del plan maestro.

Sheet CAJAS
A1: CAJAS - control de la plata real
A2: Se llena en la conciliacion de las 10:30 p.m. La reserva del premio se completa PRIMERO y no se toca.
A4: Caja | B4: Moneda | C4: Saldo | D4: En COP | E4: Nota
A5: Reserva del premio (apartada) | B5: COP | C5: 0 | D5: =C5 | E5: Los primeros COP 2.000.000. Cajita aparte. No se toca nunca.
A6: Nu (llave Bre-B @sbg884) | B6: COP | C6: 0 | D6: =C6 | E6: Solo lo verificado dentro de la app.
A7: Efectivo en mano | B7: COP | C7: 0 | D7: =C7 | E7: Anotado el mismo dia en la libreta. Nunca se publica cuanto hay.
A8: Pendiente de vendedores (efectivo) | B8: COP | C8: 0 | D8: =C8 | E8: Ruta 2: tienen 48 h para entregar.
A9: Recaudado en NZ (cuenta de Sofia) | B9: NZD | C9: 0 | D9: =C9*SUPUESTOS!$B$7 | E9: Verificado por Sofia en su propia app.
A10: Adelanto de Sofia (si gana en NZ) | B10: NZD | C10: 0 | D10: =C10*SUPUESTOS!$B$7 | E10: Se le devuelve en pesos por Bre-B a su cuenta colombiana.
A12: TOTAL EN CAJA (COP) | D12: =SUM(D5:D10)
A14: Reserva del premio completa? | D14: =IF(C5>=SUPUESTOS!$B$9,"SI","NO - faltan "&TEXT(SUPUESTOS!$B$9-C5,"#,##0")&" COP")
A16: CONCILIACION DIARIA (10:30 p.m.)
A18: Números PAGADO en el Sheet (Colombia) | C18: 0 | D18: =C18*SUPUESTOS!$B$5
A19: Números PAGADO en el Sheet (NZ) | C19: 0 | D19: =C19*SUPUESTOS!$B$8
A20: Esperado en caja | D20: =D18+D19
A21: Real en caja (fila 12) | D21: =D12
A22: Diferencia | D22: =D21-D20
A23: Si la diferencia no es cero, el dia no se cierra hasta encontrarla. Lo mas comun: un pantallazo que se tomo por pago, o un numero apartado dos veces.

Sheet VENDEDORES
A1: VENDEDORES - numeros vendidos y umbral de 25 compradores distintos
A2: El premio de COP 100.000 se paga solo si el vendedor le vendio a MAS de 25 personas distintas Y uno de sus compradores gana (decision 9). No aplica a lo que venda Santiago.
A4: Nombre | B4: Código (link ?v=) | C4: Tipo | D4: Números vendidos | E4: Compradores distintos | F4: Pasó de 25? | G4: Plata pendiente (COP) | H4: Comisión a pagar (COP)
F5: =IF(E5="","",IF(E5>25,"SI","no")) | H5: =IF(C5="TIENDA",D5*SUPUESTOS!$B$5*SUPUESTOS!$B$14,0)
F6: =IF(E6="","",IF(E6>25,"SI","no")) | H6: =IF(C6="TIENDA",D6*SUPUESTOS!$B$5*SUPUESTOS!$B$14,0)
F7: =IF(E7="","",IF(E7>25,"SI","no")) | H7: =IF(C7="TIENDA",D7*SUPUESTOS!$B$5*SUPUESTOS!$B$14,0)
F8: =IF(E8="","",IF(E8>25,"SI","no")) | H8: =IF(C8="TIENDA",D8*SUPUESTOS!$B$5*SUPUESTOS!$B$14,0)
F9: =IF(E9="","",IF(E9>25,"SI","no")) | H9: =IF(C9="TIENDA",D9*SUPUESTOS!$B$5*SUPUESTOS!$B$14,0)
F10: =IF(E10="","",IF(E10>25,"SI","no")) | H10: =IF(C10="TIENDA",D10*SUPUESTOS!$B$5*SUPUESTOS!$B$14,0)
F11: =IF(E11="","",IF(E11>25,"SI","no")) | H11: =IF(C11="TIENDA",D11*SUPUESTOS!$B$5*SUPUESTOS!$B$14,0)
F12: =IF(E12="","",IF(E12>25,"SI","no")) | H12: =IF(C12="TIENDA",D12*SUPUESTOS!$B$5*SUPUESTOS!$B$14,0)
F13: =IF(E13="","",IF(E13>25,"SI","no")) | H13: =IF(C13="TIENDA",D13*SUPUESTOS!$B$5*SUPUESTOS!$B$14,0)
F14: =IF(E14="","",IF(E14>25,"SI","no")) | H14: =IF(C14="TIENDA",D14*SUPUESTOS!$B$5*SUPUESTOS!$B$14,0)
F15: =IF(E15="","",IF(E15>25,"SI","no")) | H15: =IF(C15="TIENDA",D15*SUPUESTOS!$B$5*SUPUESTOS!$B$14,0)
F16: =IF(E16="","",IF(E16>25,"SI","no")) | H16: =IF(C16="TIENDA",D16*SUPUESTOS!$B$5*SUPUESTOS!$B$14,0)
... F24: =IF(E24="","",IF(E24>25,"SI","no")) | H24: =IF(C24="TIENDA",D24*SUPUESTOS!$B$5*SUPUESTOS!$B$14,0)
A26: TOTALES | D26: =SUM(D5:D24) | G26: =SUM(G5:G24) | H26: =SUM(H5:H24)
A28: En la columna Tipo escriba FAMILIA, AMIGO o TIENDA. Solo TIENDA genera comision del 10%.

Sheet PUNTOS-CONTROL
A1: PUNTOS DE CONTROL - vendido contra meta
A2: Si lo vendido queda por debajo del umbral del 90%, se activa el siguiente refuerzo de la escalera (ver 03_Hoja-de-ruta/puntos-de-control.md).
A4: Punto de control | B4: Fecha | C4: Meta acumulada | D4: Umbral 90% | E4: Vendido real | F4: % de la meta | G4: Refuerzo? | H4: Refuerzo activado
A5: Preventa cerrada | B5: sáb 10 - lun 12 oct | C5: 120 | D5: =ROUND(C5*0.9,0) | F5: =IF(E5="","",E5/C5) | G5: =IF(E5="","",IF(E5<D5,"SI","no"))
A6: PC 1 | B6: dom 18 oct | C6: 230 | D6: =ROUND(C6*0.9,0) | F6: =IF(E6="","",E6/C6) | G6: =IF(E6="","",IF(E6<D6,"SI","no"))
A7: PC 2 | B7: dom 25 oct | C7: 320 | D7: =ROUND(C7*0.9,0) | F7: =IF(E7="","",E7/C7) | G7: =IF(E7="","",IF(E7<D7,"SI","no"))
A8: PC 3 (Tizumba?) | B8: dom 1 nov | C8: 420 | D8: =ROUND(C8*0.9,0) | F8: =IF(E8="","",E8/C8) | G8: =IF(E8="","",IF(E8<D8,"SI","no"))
A9: PC 4 | B9: dom 8 nov | C9: 500 | D9: =ROUND(C9*0.9,0) | F9: =IF(E9="","",E9/C9) | G9: =IF(E9="","",IF(E9<D9,"SI","no"))
A10: PC 5 | B10: dom 15 nov | C10: 600 | D10: =ROUND(C10*0.9,0) | F10: =IF(E10="","",E10/C10) | G10: =IF(E10="","",IF(E10<D10,"SI","no"))
A11: PC 6 | B11: dom 22 nov | C11: 690 | D11: =ROUND(C11*0.9,0) | F11: =IF(E11="","",E11/C11) | G11: =IF(E11="","",IF(E11<D11,"SI","no"))
A12: PC 7 | B12: dom 29 nov | C12: 750 | D12: =ROUND(C12*0.9,0) | F12: =IF(E12="","",E12/C12) | G12: =IF(E12="","",IF(E12<D12,"SI","no"))
A13: Cierre (piso) | B13: sáb 5 dic | C13: 860 | D13: =ROUND(C13*0.9,0) | F13: =IF(E13="","",E13/C13) | G13: =IF(E13="","",IF(E13<D13,"SI","no"))
A14: Cierre (meta) | B14: sáb 5 dic | C14: 900 | D14: =ROUND(C14*0.9,0) | F14: =IF(E14="","",E14/C14) | G14: =IF(E14="","",IF(E14<D14,"SI","no"))
A16: Escalera de refuerzos, en orden: 1) reto de vendedores + cerrar tiendas 2) grupos de Facebook de Fusa 3) dia fuerte en la UdeC 4) publicacion de Tizumba 5) campana de numeros bonitos libres + encuestas.
A17: Solo cuentan los numeros PAGADO. Los apartados no cuentan.
